Adafruit_WS2801/__init__.py
Adafruit_WS2801/WS2801.py
Adafruit_WS2801-1.0.1.dist-info/metadata.json
Adafruit_WS2801-1.0.1.dist-info/METADATA
Adafruit_WS2801-1.0.1.dist-info/RECORD
Adafruit_WS2801-1.0.1.dist-info/WHEEL
Adafruit_WS2801-1.0.1.dist-info/DESCRIPTION.rst
Adafruit_WS2801-1.0.1.dist-info/dependency_links.txt
Adafruit_WS2801-1.0.1.dist-info/top_level.txt
