Metadata-Version: 1.1
Name: Adafruit-WS2801
Version: 1.0.1
Summary: Python code to control WS2801 and similar SPI interface addressable RGB LED strips on a Raspberry Pi & BeagleBone Black.
Home-page: https://github.com/adafruit/Adafruit_Python_WS2801/
Author: Tony DiCola
Author-email: tdicola@adafruit.com
License: MIT
Platform: UNKNOWN
Classifier: Development Status :: 4 - Beta
Classifier: Operating System :: POSIX :: Linux
Classifier: License :: OSI Approved :: MIT License
Classifier: Intended Audience :: Developers
Classifier: Programming Language :: Python :: 2.7
Classifier: Programming Language :: Python :: 3
Classifier: Topic :: Software Development
Classifier: Topic :: System :: Hardware
